ptcime-1.0.4.data/scripts/ptcime
time_tracking/__init__.py
time_tracking/__main__.py
time_tracking/parsing.py
time_tracking/time_tracking.py
ptcime-1.0.4.dist-info/LICENSE
ptcime-1.0.4.dist-info/METADATA
ptcime-1.0.4.dist-info/WHEEL
ptcime-1.0.4.dist-info/top_level.txt
ptcime-1.0.4.dist-info/RECORD
