Metadata-Version: 2.1
Name: ptcime
Version: 1.0.4
Summary: A simple time tracking script.
Home-page: https://github.com/ptcar2009/ptcime
Author: Pedro Tavares de Carvalho
Author-email: ptcar2009@gmail.com
License: UNKNOWN
Platform: UNKNOWN
Classifier: Programming Language :: Python :: 3
Classifier: License :: OSI Approved :: MIT License
Classifier: Operating System :: OS Independent
Requires-Python: >=3.6
